QueryLMS/QueryLMS.py
QueryLMS/__init__.py
QueryLMS/constants.py
QueryLMS-0.2.5.0.dist-info/LICENSE
QueryLMS-0.2.5.0.dist-info/METADATA
QueryLMS-0.2.5.0.dist-info/WHEEL
QueryLMS-0.2.5.0.dist-info/top_level.txt
QueryLMS-0.2.5.0.dist-info/RECORD
