Metadata-Version: 2.1
Name: QueryLMS
Version: 0.2.5.0
Summary: Simple interface for making queries and issuing commands to Logitech Media Server and associated players
Home-page: https://github.com/txoof/querylms
Author: Aaron Ciuffo
Author-email: aaron.ciuffo@gmail.com
Project-URL: Source, https://github.com/txoof/querylms
Keywords: graphics e-paper display waveshare
Classifier: Intended Audience :: Developers
Classifier: Topic :: Software Development :: Libraries :: Python Modules
Classifier: Programming Language :: Python :: 3.7
Classifier: License :: OSI Approved :: GNU General Public License v3 or later (GPLv3+)
Classifier: Operating System :: OS Independent
Requires-Python: >=3.7
License-File: LICENSE
Requires-Dist: requests
